pytoc/__init__.py
pytoc/pytoc.py
pytoc-0.0.3.dist-info/LICENSE
pytoc-0.0.3.dist-info/METADATA
pytoc-0.0.3.dist-info/WHEEL
pytoc-0.0.3.dist-info/top_level.txt
pytoc-0.0.3.dist-info/RECORD
