Metadata-Version: 2.1
Name: pytoc
Version: 0.0.3
Summary: A Python library for generating Total Operating Characteristic (TOC) Curves.
Home-page: https://github.com/lazygis/pytoc
Author: Zhen Liu
Author-email: zhenliu26@outlook.com
License: UNKNOWN
Platform: UNKNOWN
Classifier: Programming Language :: Python :: 3
Classifier: License :: OSI Approved :: MIT License
Classifier: Operating System :: OS Independent
License-File: LICENSE
Requires-Dist: matplotlib
Requires-Dist: numpy
